spotify_dlx/__init__.py
spotify_dlx/__main__.py
spotify_dlx/spotify_dlx.py
spotify_dlx/utils.py
spotify_dlx-0.2.0.dist-info/LICENSE
spotify_dlx-0.2.0.dist-info/METADATA
spotify_dlx-0.2.0.dist-info/WHEEL
spotify_dlx-0.2.0.dist-info/dependency_links.txt
spotify_dlx-0.2.0.dist-info/entry_points.txt
spotify_dlx-0.2.0.dist-info/top_level.txt
spotify_dlx-0.2.0.dist-info/RECORD
