Metadata-Version: 2.1
Name: spotify-dlx
Version: 0.2.0
Summary: Download songs from Spotify like youtube-dl
Home-page: https://github.com/ozora-ogino/spotify_dlx/
Author: ozora-ogino
License: UNKNOWN
Platform: UNKNOWN
Requires-Dist: music-tag
Requires-Dist: pydub
Requires-Dist: rich
Requires-Dist: requests
Requires-Dist: yaspin
Provides-Extra: test
Requires-Dist: black ; extra == 'test'
Requires-Dist: pytest ; extra == 'test'
Requires-Dist: pre-commit ; extra == 'test'
